LICENSE
MANIFEST.in
README.md
setup.py
src/wheezy/__init__.py
src/wheezy.core.egg-info/PKG-INFO
src/wheezy.core.egg-info/SOURCES.txt
src/wheezy.core.egg-info/dependency_links.txt
src/wheezy.core.egg-info/namespace_packages.txt
src/wheezy.core.egg-info/not-zip-safe
src/wheezy.core.egg-info/top_level.txt
src/wheezy/core/__init__.py
src/wheezy/core/benchmark.py
src/wheezy/core/collections.py
src/wheezy/core/config.py
src/wheezy/core/datetime.py
src/wheezy/core/db.py
src/wheezy/core/descriptors.py
src/wheezy/core/feistel.py
src/wheezy/core/gzip.py
src/wheezy/core/httpclient.py
src/wheezy/core/i18n.py
src/wheezy/core/introspection.py
src/wheezy/core/json.py
src/wheezy/core/luhn.py
src/wheezy/core/mail.py
src/wheezy/core/pooling.py
src/wheezy/core/retry.py
src/wheezy/core/url.py
src/wheezy/core/uuid.py