Metadata-Version: 2.1
Name: wheezy.core
Version: 3.0.0
Summary: A lightweight core library
Home-page: https://github.com/akornatskyy/wheezy.core
Author: Andriy Kornatskyy
Author-email: andriy.kornatskyy@live.com
License: MIT
Keywords: core benchmark collections config datetime db descriptor feistel i18n introspection json luhn mail pooling url uuid
Platform: any
Classifier: Intended Audience :: Developers
Classifier: License :: OSI Approved :: MIT License
Classifier: Natural Language :: English
Classifier: Operating System :: OS Independent
Classifier: Programming Language :: Python
Classifier: Programming Language :: Python :: 3.6
Classifier: Programming Language :: Python :: 3.7
Classifier: Programming Language :: Python :: 3.8
Classifier: Programming Language :: Python :: 3.9
Classifier: Programming Language :: Python :: Implementation :: CPython
Classifier: Programming Language :: Python :: Implementation :: PyPy
Classifier: Topic :: Software Development :: Libraries :: Python Modules
Classifier: Topic :: Software Development :: Internationalization
Classifier: Topic :: Software Development :: Localization
Classifier: Topic :: System :: Benchmark
Requires-Python: >=3.6
